README.md
setup.py
ratelang/__init__.py
ratelang.egg-info/PKG-INFO
ratelang.egg-info/SOURCES.txt
ratelang.egg-info/dependency_links.txt
ratelang.egg-info/top_level.txt