Metadata-Version: 2.1
Name: ratelang
Version: 0.0.1.dev0
Summary: Experiment.
Home-page: UNKNOWN
Author: Sylvain Bellemare
License: MIT license
Platform: UNKNOWN
Classifier: Development Status :: 1 - Planning
Classifier: Intended Audience :: Developers
Classifier: License :: OSI Approved :: MIT License
Classifier: Natural Language :: English
Classifier: Operating System :: POSIX :: Linux
Classifier: Programming Language :: Python :: 3
Classifier: Programming Language :: Python :: 3.7
Classifier: Programming Language :: Python :: 3.8
Requires-Python: >=3.7
